unishox2.pypy37-pp73-darwin.so
unishox2_py3-1.0.0.dist-info/LICENSE
unishox2_py3-1.0.0.dist-info/METADATA
unishox2_py3-1.0.0.dist-info/WHEEL
unishox2_py3-1.0.0.dist-info/top_level.txt
unishox2_py3-1.0.0.dist-info/RECORD
