Metadata-Version: 2.1
Name: unishox2-py3
Version: 1.0.0
Summary: A package for Unicode-friendly string compression using Unishox2
Home-page: https://chris.partridge.tech/
Author: Chris Partridge
Author-email: tweedge-public@partridge.tech
License: Apache License 2.0
Project-URL: Source, https://github.com/tweedge/unishox2-py3
Platform: UNKNOWN
Classifier: Development Status :: 5 - Production/Stable
Classifier: License :: OSI Approved :: Apache Software License
Classifier: Operating System :: MacOS
Classifier: Operating System :: Microsoft :: Windows
Classifier: Operating System :: POSIX :: Linux
Classifier: Programming Language :: C
Classifier: Programming Language :: Cython
Classifier: Programming Language :: Python
Classifier: Programming Language :: Python :: 3
Classifier: Programming Language :: Python :: 3.6
Classifier: Programming Language :: Python :: 3.7
Classifier: Programming Language :: Python :: 3.8
Classifier: Programming Language :: Python :: 3.9
Classifier: Programming Language :: Python :: 3.10
Classifier: Topic :: Software Development :: Libraries
Classifier: Topic :: System :: Archiving :: Compression
License-File: LICENSE
